invitation/__init__.py
invitation/builder.py
invitation/main.py
invitation/model.py
invitation/templates/invitation.tex.jinja
invitation/templates/letter.tex.jinja
invitation/util.py
uk_invitation_letter-0.7.2.dist-info/METADATA
uk_invitation_letter-0.7.2.dist-info/WHEEL
uk_invitation_letter-0.7.2.dist-info/entry_points.txt
uk_invitation_letter-0.7.2.dist-info/licenses/LICENSE.md
uk_invitation_letter-0.7.2.dist-info/RECORD
