Metadata-Version: 2.4
Name: uk-invitation-letter
Version: 0.7.2
Summary: UK visa invitation letter generator.
License: LGPL-3.0-or-later
License-File: LICENSE.md
Author: Timur Iskhakov
Author-email: me@timur.is
Requires-Python: >=3.10,<4.0
Classifier: Development Status :: 4 - Beta
Classifier: Environment :: Console
Classifier: Intended Audience :: Legal Industry
Classifier: License :: OSI Approved :: GNU Lesser General Public License v3 or later (LGPLv3+)
Classifier: Natural Language :: English
Classifier: Operating System :: OS Independent
Classifier: Programming Language :: Python :: 3
Classifier: Programming Language :: Python :: 3.10
Classifier: Programming Language :: Python :: 3.11
Classifier: Programming Language :: Python :: 3.12
Classifier: Programming Language :: Python :: 3.13
Classifier: Programming Language :: Python :: 3.14
Classifier: Topic :: Text Processing :: Markup :: LaTeX
Requires-Dist: Jinja2 (>=3.1.6,<4.0.0)
Requires-Dist: phonenumbers (>=9.0.21,<10.0.0)
Requires-Dist: pydantic (>=2.12.5,<3.0.0)
Requires-Dist: pydantic-yaml (>=1.6.0,<2.0.0)
Project-URL: Repository, https://github.com/iskhakovt/uk-invitation-letter
